IotPervasiveServiceSDK/__init__.py
IotPervasiveServiceSDK/config.py
IotPervasiveServiceSDK/proxySDK.py
IotPervasiveServiceSDK/core/applicationContext.py
IotPervasiveServiceSDK/core/eventInvoker.py
IotPervasiveServiceSDK/core/scheduleService.py
IotPervasiveServiceSDK/core/serverInvoker.py
IotPervasiveServiceSDK/core/exception/commonException.py
IotPervasiveServiceSDK/core/exception/sdkException.py
IotPervasiveServiceSDK/core/exception/serviceException.py
IotPervasiveServiceSDK/core/job/contextUpLoadJob.py
IotPervasiveServiceSDK/core/job/eventListenerJob.py
IotPervasiveServiceSDK/core/job/mqttCheckMessageJob.py
IotPervasiveServiceSDK/core/job/mqttHealthJob.py
IotPervasiveServiceSDK/core/loader/hardwareInfoLoader.py
IotPervasiveServiceSDK/core/loader/proxyLoader.py
IotPervasiveServiceSDK/core/loader/serversLoader.py
IotPervasiveServiceSDK/core/loader/thingProxyFuncLoader.py
IotPervasiveServiceSDK/core/sender/baseSender.py
IotPervasiveServiceSDK/core/sender/hardwareUpLoadSender.py
IotPervasiveServiceSDK/factory/systemEventFactory.py
IotPervasiveServiceSDK/factory/systemServiceFactory.py
IotPervasiveServiceSDK/model/ujinja/source.py
IotPervasiveServiceSDK/pojo/capabilityBean.py
IotPervasiveServiceSDK/pojo/eventBean.py
IotPervasiveServiceSDK/pojo/serviceBean.py
IotPervasiveServiceSDK/proxy/proxyBase.py
IotPervasiveServiceSDK/proxy/pythonServiceProxy.py
IotPervasiveServiceSDK/proxy/thingProxy.py
IotPervasiveServiceSDK/router/httpRouter.py
IotPervasiveServiceSDK/router/mqttRouter.py
IotPervasiveServiceSDK/systemService/httpService.py
IotPervasiveServiceSDK/systemService/mqttService.py
IotPervasiveServiceSDK/systemService/updateService.py
IotPervasiveServiceSDK/utils/TimeUtil.py
IotPervasiveServiceSDK/utils/copyUtils.py
IotPervasiveServiceSDK/utils/fileUtils.py
IotPervasiveServiceSDK/utils/logutil.py
IotPervasiveServiceSDK/utils/netUtils.py
IotPervasiveServiceSDK/utils/pathUtils.py
IotPervasiveServiceSDK/utils/tarGzUtils.py
IotPervasiveServiceSDK/utils/taskUtils.py
iot_sdk_demo-0.0.5.dist-info/LICENSE
iot_sdk_demo-0.0.5.dist-info/METADATA
iot_sdk_demo-0.0.5.dist-info/WHEEL
iot_sdk_demo-0.0.5.dist-info/top_level.txt
iot_sdk_demo-0.0.5.dist-info/RECORD
