Metadata-Version: 2.1
Name: iot-sdk-demo
Version: 0.0.5
Summary: A small example package
Home-page: https://github.com/pypa/sampleproject
Author: HFC
Author-email: 2898534520@qq.com
Classifier: Programming Language :: Python :: 3
Classifier: License :: OSI Approved :: MIT License
Classifier: Operating System :: OS Independent
Requires-Python: >=3.6
License-File: LICENSE
Requires-Dist: bottle (==0.12.25)
Requires-Dist: netifaces (==0.11.0)
Requires-Dist: paho-mqtt (==1.6.1)
Requires-Dist: psutil (==5.9.4)
Requires-Dist: Requests (>=2.0.0)
Requires-Dist: ujson
